[{
     "sl": 1,
     "refundId": 1001,
    "orderId": 100195,
    "customerInfo": "Md.Jabed Hossain",
    "phone": "01712345678",
    "totalAmount": 5000000,
    "image":"https://unsplash.com/photos/dead-trees-in-a-vast-desert-landscape-w_rVpVZGa3g",
    "productInfo":"Bicycle",
    "quentity": 5
    
},
{
    "sl": 20,
     "refundId": 1002,
    "orderId": 100196,
    "customerInfo": "Md.Jabed Hossain",
    "phone": "01712345678",
    "totalAmount": 5000000,
    "image":"https://unsplash.com/photos/dead-trees-in-a-vast-desert-landscape-w_rVpVZGa3g",
    "productInfo":"Motorcycle",
    "quentity": 30
},
{
    "sl": 30,
     "refundId": 1003,
    "orderId": 100197,
    "customerInfo": "Md.Jabed Hossain",
    "phone": "01712345678",
    "totalAmount": 5000000,
    "image":"https://unsplash.com/photos/dead-trees-in-a-vast-desert-landscape-w_rVpVZGa3g",
    "productInfo":"Laptop",
    "quentity": 20
},
{
    "sl": 40,
     "refundId": 1004,
    "orderId": 100198,
    "customerInfo": "Md.Jabed Hossain",
    "phone": "01712345678",
    "totalAmount": 5000000,
    "image":"https://unsplash.com/photos/dead-trees-in-a-vast-desert-landscape-w_rVpVZGa3g",
    "productInfo":"PrivateCar********",
    "quentity": 10
}


]
